{
	"name": "DS_Learning_Storage",
	"properties": {
		"linkedServiceName": {
			"referenceName": "LS_LearningBlobStorage",
			"type": "LinkedServiceReference"
		},
		"folder": {
			"name": "Learning"
		},
		"annotations": [],
		"type": "DelimitedText",
		"typeProperties": {
			"location": {
				"type": "AzureBlobStorageLocation",
				"fileName": "employee.csv",
				"folderPath": "Employee",
				"container": "cktcontainer"
			},
			"columnDelimiter": ",",
			"escapeChar": "\\",
			"quoteChar": "\""
		},
		"schema": []
	}
}