{
	"name": "Last15Days",
	"properties": {
		"annotations": [],
		"runtimeState": "Started",
		"pipelines": [
			{
				"pipelineReference": {
					"referenceName": "AggregateDataPipeline",
					"type": "PipelineReference"
				},
				"parameters": {
					"LastNumberOfDays_PipeLine": 15
				}
			}
		],
		"type": "ScheduleTrigger",
		"typeProperties": {
			"recurrence": {
				"frequency": "Day",
				"interval": 1,
				"startTime": "2020-08-14T05:37:00Z",
				"timeZone": "UTC",
				"schedule": {
					"minutes": [
						0
					],
					"hours": [
						8
					]
				}
			}
		}
	}
}